postgresql_notification_listener/__init__.py
postgresql_notification_listener/listener.py
postgresql_notification_listener/py.typed
postgresql_notification_listener/types.py
postgresql_notification_listener-2.0.2.dist-info/LICENSE
postgresql_notification_listener-2.0.2.dist-info/METADATA
postgresql_notification_listener-2.0.2.dist-info/WHEEL
postgresql_notification_listener-2.0.2.dist-info/RECORD
