Metadata-Version: 2.1
Name: postgresql-notification-listener
Version: 2.0.2
Summary: Execute functions on PostgreSQL notifications
Home-page: https://github.com/tvuotila/postgresql-notification-listener
License: MIT
Author: Tero Vuotila
Author-email: tero.vuotila@falcony.io
Requires-Python: >=3.10
Classifier: Development Status :: 5 - Production/Stable
Classifier: Intended Audience :: Developers
Classifier: License :: OSI Approved :: MIT License
Classifier: Programming Language :: Python :: 3
Classifier: Programming Language :: Python :: 3.10
Classifier: Programming Language :: Python :: 3.11
Classifier: Programming Language :: Python :: 3.12
Classifier: Programming Language :: Python :: 3.13
Classifier: Topic :: Software Development :: Libraries :: Python Modules
Requires-Dist: psycopg (<4)
Project-URL: Repository, https://github.com/tvuotila/postgresql-notification-listener
